Workbook

Sheet Inputs
B2: Variabelen
B3: ratio stroom/ex stroom | C3: 0.15 | D3: tussen 0% en 100%
B4: Salesteam | C4: Ja | D4: Ja / nee
B5: Vervolgcampagne | C5: Ja | D5: Ja / nee
B9: Maandprijs VanMossel | C9: 801
B10: Users to vehicles ratio | C10: 1.4

Sheet Toelichting cijfers
B2: 2024: Officiele start, platformbouw en assets
B3: In de eerste helft van 2024 hebben we de MVP van het Blueplates-platform ontwikkeld en gelanceerd, waarmee we de inzichten uit de voorgaande pilotfase hebben vertaald naar een schaalbare technologische infrastructuur. Parallel daaraan zijn we, met financiering van AKEF, gestart met het opbouwen van een eerste vloot voertuigen. Deze voertuigen vormen de initiële kern van het platform en maken het mogelijk om vraag en aanbod te organiseren vanuit één operationeel systeem. Rond deze kern bouwen we een flexibel netwerk van voertuigen via lease- en partnerstructuren. Omdat de voertuigen pas tegen het einde van het jaar volledig operationeel werden binnen de nieuwe app, weerspiegelen de cijfers van 2024 grotendeels de investerings- en opstartfase. De hogere OPEX bestaat voornamelijk uit investeringen in productontwikkeling, technologie en de opbouw van de operationele infrastructuur die nodig is om het platform op schaal te laten functioneren.
B5: 2025: Commerciële opschaling en optimalisatie
B6: 2025 stond in het teken van de volledige uitrol van het eigen Blueplates-platform en de opschaling van klantacquisitie. In deze fase hebben we onze prijsstrategie verder geoptimaliseerd om beter aan te sluiten bij een groeiende en meer langdurige klantenbasis. Tijdens deze optimalisatieperiode lag de bezettingsgraad tijdelijk lager, terwijl we tegelijkertijd bleven investeren in productontwikkeling. Naarmate de prijsstructuur en het platform verder werden verfijnd, nam de bezettingsgraad gedurende het jaar sterk toe en bereikte deze tegen het einde van het jaar meer dan 85%. In combinatie met het gebruik van eigen voertuigen resulteerde dit in duidelijk verbeterde operationele prestaties en een brutomarge van circa 27%.
B8: 2026: Opschaling en ontwikkeling van asset-light infrastructuur
B9: De eerste maanden van 2026 laten zien dat de positieve ontwikkeling zich voortzet. De focus ligt dit jaar op verdere schaalvergroting, voortbouwend op de stabiele basis die in de voorgaande jaren is gelegd. In deze fase richten we ons nadrukkelijk op het aangaan en verdiepen van strategische partnerschappen om het aantal chauffeurs, voertuigen en klanten versneld te laten groeien. Tegelijkertijd wordt het platform verder uitgebreid, met functionaliteiten die de incentives van de drie belangrijkste partijen in het taxiecosysteem (platforms, voertuigleveranciers en chauffeurs) beter op elkaar afstemmen. Deze aanpak ondersteunt de overgang naar een meer asset-light infrastructuur en creëert de voorwaarden voor snellere schaalbaarheid, een grotere netwerkdynamiek en verdere verbetering van de marges.

Sheet Jaarcijfers
C2: 2024 | D2: 2025 | E2: 2026 | F2: 2027 | G2: 2028
B3: Omzet | C3: 300851 | D3: 375382.25 | E3: =SUMIFS(Forecast!$C$16:$V$16,Forecast!$C$3:$V$3,Jaarcijfers!E$2) -> 1048166 | F3: =SUMIFS(Forecast!$C$16:$V$16,Forecast!$C$3:$V$3,Jaarcijfers!F$2) -> 2890113.8 | G3: =SUMIFS(Forecast!$C$16:$V$16,Forecast!$C$3:$V$3,Jaarcijfers!G$2) -> 6190329.5
B4: directe kosten | C4: 312555 | D4: 272906.63 | E4: =SUMIFS(Forecast!$C$27:$V$27,Forecast!$C$3:$V$3,Jaarcijfers!E$2) -> 694384.31 | F4: =SUMIFS(Forecast!$C$27:$V$27,Forecast!$C$3:$V$3,Jaarcijfers!F$2) -> 1634831.8 | G4: =SUMIFS(Forecast!$C$27:$V$27,Forecast!$C$3:$V$3,Jaarcijfers!G$2) -> 2653910.8
B5: Brutowinst | C5: =C3-C4 -> -11704 | D5: =D3-D4 -> 102475.62 | E5: =E3-E4 -> 353781.71 | F5: =F3-F4 -> 1255281.9 | G5: =G3-G4 -> 3536418.7
B6: Verkoop- en algemene kosten | C6: 287811 | D6: 578389.37 | E6: =SUMIFS(Forecast!$C$40:$V$40,Forecast!$C$3:$V$3,Jaarcijfers!E$2) -> 628814.97 | F6: =SUMIFS(Forecast!$C$40:$V$40,Forecast!$C$3:$V$3,Jaarcijfers!F$2) -> 946855.34 | G6: =SUMIFS(Forecast!$C$40:$V$40,Forecast!$C$3:$V$3,Jaarcijfers!G$2) -> 1104133.1
B7: EBITDA | C7: =C5-C6 -> -299515 | D7: =D5-D6 -> -475913.75 | E7: =E5-E6 -> -275033.26 | F7: =F5-F6 -> 308426.6 | G7: =G5-G6 -> 2432285.6
B8: Afschrijvingen | C8: 9638 | D8: 83537.65
B9: EBIT | C9: =C7-C8 -> -309153 | D9: =D7-D8 -> -559451.4
B10: Financiele baten (lasten) | D10: 2435.79
B11: Rente lening | C11: 62948 | D11: 104165.81
B12: Resultaat voor belasting | C12: =C9-C10-C11 -> -372101 | D12: =D9-D10-D11 -> -666053
C16: 45657 | D16: 46022
B17: Activa
B18: Vaste activa | C18: =1299597+87780+149 -> 1387526 | D18: 1297732.7
B19: Vlottende activa | C19: 288819 | D19: 414931.6
B20: Liquide middelen | C20: 38343 | D20: 22948.25
C21: =SUM(C18:C20) -> 1714688 | D21: 1735612.5
B23: Passiva
B24: Eigen vermogen | C24: =-379215+372116 -> -7099 | D24: -543409.03
B25: Lange schulden | C25: =968094+187233 -> 1155327 | D25: 1746307.5
B26: Korte schulden | C26: 566460 | D26: 532714.05
C27: =SUM(C24:C26) -> 1714688 | D27: 1735612.5

Sheet Forecast
B1: inflatiecorrectie | C1: 1 | D1: 1.0025 | E1: 1.005 | F1: 1.0075 | G1: 1.01 | H1: 1.0125 | I1: 1.015 | J1: 1.0175 | K1: 1.02 | L1: 1.0225 | M1: 1.025 | N1: 1.0275 | O1: 1.035 | P1: 1.0425 | Q1: 1.05 | R1: 1.0575 | S1: 1.065 | T1: 1.0725 | U1: 1.08 | V1: 1.0875
C3: 2026 | D3: 2026 | E3: 2026 | F3: 2026 | G3: 2026 | H3: 2026 | I3: 2026 | J3: 2026 | K3: 2026 | L3: 2026 | M3: 2026 | N3: 2026 | O3: 2027 | P3: 2027 | Q3: 2027 | R3: 2027 | S3: 2028 | T3: 2028 | U3: 2028 | V3: 2028
C4: Jan | D4: Feb | E4: Mar | F4: Apr | G4: May | H4: Jun | I4: Jul | J4: Aug | K4: Sep | L4: Oct | M4: Nov | N4: Dec | O4: Q1 | P4: Q2 | Q4: Q3 | R4: Q4 | S4: Q1 | T4: Q2 | U4: Q3 | V4: Q4
A5: Occupancy rate | B5: Bezettingsgraad | C5: 0.85 | D5: 0.85 | E5: 0.85 | F5: 0.9 | G5: 0.9 | H5: 0.9 | I5: 0.85 | J5: 0.85 | K5: 0.95 | L5: 0.95 | M5: 0.95 | N5: 0.95 | O5: 0.95 | P5: 0.95 | Q5: 0.95 | R5: 0.95 | S5: 0.95 | T5: 0.95 | U5: 0.95 | V5: 0.95
A6: Lease (Ayvens) | B6: Lease (Ayvens) | C6: 4 | D6: 4 | E6: 4 | F6: 4 | G6: 4 | H6: 4 | I6: 4 | J6: 4 | K6: 4 | L6: 4 | M6: 4 | N6: 4 | O6: 4 | P6: 4 | Q6: 4 | R6: 4 | S6: 4 | T6: 4 | U6: 4 | V6: 4
A7: Lease (Van Mossel) +5 per month | B7: Lease (Van Mossel) +5pm (begin halverwege Feb) | C7: 0 | D7: 2.5 | E7: =D7+5 -> 7.5 | F7: =E7+5 -> 12.5 | G7: =F7+5 -> 17.5 | H7: =G7+5 -> 22.5 | I7: =H7+5 -> 27.5 | J7: =I7+5 -> 32.5 | K7: =J7+5 -> 37.5 | L7: =K7+5 -> 42.5 | ... N7: =M7+5 -> 52.5 | O7: =N7+10 -> 62.5 | P7: =O7+15 -> 77.5 | Q7: =P7+15 -> 92.5 | R7: =Q7+15 -> 107.5 | S7: =R7+15 -> 122.5 | T7: =S7+15 -> 137.5 | U7: =T7+15 -> 152.5 | V7: =U7+15 -> 167.5
A8: Tesla (bought) | B8: Tesla (koop) | C8: 5 | D8: 5 | E8: 5 | F8: 9 | G8: =F8 -> 9 | H8: =G8 -> 9 | I8: =H8 -> 9 | J8: =I8 -> 9 | K8: =J8 -> 9 | L8: =K8 -> 9 | M8: =L8 -> 9 | N8: =M8 -> 9 | ... V8: =U8 -> 9
A9: NIO (bought) | B9: NIO (koop) | C9: 20 | D9: 20 | E9: 20 | F9: 20 | G9: 20 | H9: 20 | I9: 20 | J9: 20 | K9: 20 | L9: 20 | M9: 20 | N9: 20 | O9: 20 | P9: 20 | Q9: 20 | R9: 20 | S9: 20 | T9: 20 | U9: 20 | V9: 20
A10: Weekly price standard | B10: Weekprijs standard | C10: =(250*0.7+299*0.3)*C1 -> 264.7 | D10: =(250*0.7+299*0.3)*D1 -> 265.36175 | E10: =(265*0.7+299*0.3)*E1 -> 276.576 | F10: =(265*0.7+299*0.3)*F1 -> 277.264 | G10: =(265*0.7+299*0.3)*G1 -> 277.952 | H10: =(265*0.7+299*0.3)*H1 -> 278.64 | I10: =(265*0.7+299*0.3)*I1 -> 279.328 | J10: =(265*0.7+299*0.3)*J1 -> 280.016 | K10: =(265*0.7+299*0.3)*K1 -> 280.704 | L10: =(265*0.7+299*0.3)*L1 -> 281.392 | ... V10: =(265*0.7+299*0.3)*V1 -> 299.28
A11: Weekly price premium | B11: Weekprijs premium | C11: =(299*0.7+375*0.3)*C1 -> 321.8 | D11: =(299*0.7+375*0.3)*D1 -> 322.6045 | E11: =(299*0.7+375*0.3)*E1 -> 323.409 | F11: =(299*0.7+375*0.3)*F1 -> 324.2135 | G11: =(299*0.7+375*0.3)*G1 -> 325.018 | H11: =(299*0.7+375*0.3)*H1 -> 325.8225 | I11: =(299*0.7+375*0.3)*I1 -> 326.627 | J11: =(299*0.7+375*0.3)*J1 -> 327.4315 | ... V11: =(299*0.7+375*0.3)*V1 -> 349.9575
A12: Driveplan adoption rate (own fleet) | B12: Driveplan adoptie (eigen vloot) | O12: =O20*0.65 -> 62.075 | P12: =P20*0.65 -> 71.825 | Q12: =Q20*0.65 -> 81.575 | R12: =R20*0.65 -> 91.325 | S12: =S20*0.65 -> 101.075 | T12: =T20*0.65 -> 110.825 | U12: =U20*0.65 -> 120.575 | V12: =V20*0.65 -> 130.325
A13: Driveplan adoption rate (partners) | B13: Driveplan adoptie (partners) | Q13: 200 | R13: =Q13+200 -> 400 | S13: =R13+200 -> 600 | T13: =S13+200 -> 800 | U13: =T13+200 -> 1000 | V13: =U13+200 -> 1200
A14: Driveplan revenue | B14: Driveplan omzet | O14: =3*(O12*200+O13*200)*O1 -> 38548.575 | P14: =3*(P12*200+P13*200)*P1 -> 44926.537 | Q14: =3*(Q12*200+Q13*200)*Q1 -> 177392.25 | R14: =3*(R12*200+R13*200)*R1 -> 311745.71 | S14: =3*(S12*200+S13*200)*S1 -> 447986.92 | T14: =3*(T12*200+T13*200)*T1 -> 586115.89 | U14: =3*(U12*200+U13*200)*U1 -> 726132.6 | V14: =3*(V12*200+V13*200)*V1 -> 868037.06
A15: Additional purchased kilometers (avg. 400 km extra per month per vehicle, less after Driveplan) | B15: extra bijgekochte kilometers (gem. 400km per extra per voertuig) | C15: =C5*SUM(C6:C9)*400 -> 9860 | D15: =D5*SUM(D6:D9)*400 -> 10710 | E15: =E5*SUM(E6:E9)*400 -> 12410 | F15: =F5*SUM(F6:F9)*400 -> 16380 | G15: =G5*SUM(G6:G9)*400 -> 18180 | H15: =H5*SUM(H6:H9)*400 -> 19980 | I15: =I5*SUM(I6:I9)*400 -> 20570 | J15: =J5*SUM(J6:J9)*400 -> 22270 | ... N15: =N5*SUM(N6:N9)*400 -> 32490 | O15: =O5*(SUM(O6:O9)-O12)*400*3 -> 38104.5 | P15: =P5*(SUM(P6:P9)-P12)*400*3 -> 44089.5 | Q15: =Q5*(SUM(Q6:Q9)-Q12)*400*3 -> 50074.5 | R15: =R5*(SUM(R6:R9)-R12)*400*3 -> 56059.5 | S15: =S5*(SUM(S6:S9)-S12)*400*3 -> 62044.5 | T15: =T5*(SUM(T6:T9)-T12)*400*3 -> 68029.5 | U15: =U5*(SUM(U6:U9)-U12)*400*3 -> 74014.5 | V15: =V5*(SUM(V6:V9)-V12)*400*3 -> 79999.5
A16: Total Revenue | B16: Omzet | C16: =(52/12)*C5* ((C10*C6+200*C6*Inputs!$C$3) +(C10*C7+200*C7*Inputs!$C$3) +(C10*C8+200*C8*Inputs!$C$3) +(C11*C9+200*C9*Inputs!$C$3) +C15*0.17*C1) -> 41859.242 | D16: =(52/12)*D5* ((D10*D6+200*D6*Inputs!$C$3) +(D10*D7+200*D7*Inputs!$C$3) +(D10*D8+200*D8*Inputs!$C$3) +(D11*D9+200*D9*Inputs!$C$3) +D15*0.17*D1) -> 45209.24 | E16: =(52/12)*E5* ((E10*E6+200*E6*Inputs!$C$3) +(E10*E7+200*E7*Inputs!$C$3) +(E10*E8+200*E8*Inputs!$C$3) +(E11*E9+200*E9*Inputs!$C$3) +E15*0.17*E1) -> 52476.201 | F16: =(52/12)*F5* ((F10*F6+200*F6*Inputs!$C$3) +(F10*F7+200*F7*Inputs!$C$3) +(F10*F8+200*F8*Inputs!$C$3) +(F11*F9+200*F9*Inputs!$C$3) +F15*0.17*F1) -> 69127.447 | G16: =(52/12)*G5* ((G10*G6+200*G6*Inputs!$C$3) +(G10*G7+200*G7*Inputs!$C$3) +(G10*G8+200*G8*Inputs!$C$3) +(G11*G9+200*G9*Inputs!$C$3) +G15*0.17*G1) -> 76496.168 | H16: =(52/12)*H5* ((H10*H6+200*H6*Inputs!$C$3) +(H10*H7+200*H7*Inputs!$C$3) +(H10*H8+200*H8*Inputs!$C$3) +(H11*H9+200*H9*Inputs!$C$3) +H15*0.17*H1) -> 83897.687 | I16: =(52/12)*I5* ((I10*I6+200*I6*Inputs!$C$3) +(I10*I7+200*I7*Inputs!$C$3) +(I10*I8+200*I8*Inputs!$C$3) +(I11*I9+200*I9*Inputs!$C$3) +I15*0.17*I1) -> 85488.979 | J16: =(52/12)*J5* ((J10*J6+200*J6*Inputs!$C$3) +(J10*J7+200*J7*Inputs!$C$3) +(J10*J8+200*J8*Inputs!$C$3) +(J11*J9+200*J9*Inputs!$C$3) +J15*0.17*J1) -> 92475.65 | ... N16: =(52/12)*N5* ((N10*N6+200*N6*Inputs!$C$3) +(N10*N7+200*N7*Inputs!$C$3) +(N10*N8+200*N8*Inputs!$C$3) +(N11*N9+200*N9*Inputs!$C$3) +N15*0.17*N1) -> 137391.63 | O16: =3*(52/12)*O5* ((O10*O6+200*O6*Inputs!$C$3) +(O10*O7+200*O7*Inputs!$C$3) +(O10*O8+200*O8*Inputs!$C$3) +(O11*O9+200*O9*Inputs!$C$3) +O15*0.17*O1)+O14 -> 504582.78 | P16: =3*(52/12)*P5* ((P10*P6+200*P6*Inputs!$C$3) +(P10*P7+200*P7*Inputs!$C$3) +(P10*P8+200*P8*Inputs!$C$3) +(P11*P9+200*P9*Inputs!$C$3) +P15*0.17*P1)+P14 -> 585885.93 | Q16: =3*(52/12)*Q5* ((Q10*Q6+200*Q6*Inputs!$C$3) +(Q10*Q7+200*Q7*Inputs!$C$3) +(Q10*Q8+200*Q8*Inputs!$C$3) +(Q11*Q9+200*Q9*Inputs!$C$3) +Q15*0.17*Q1)+Q14 -> 794230.02 | R16: =3*(52/12)*R5* ((R10*R6+200*R6*Inputs!$C$3) +(R10*R7+200*R7*Inputs!$C$3) +(R10*R8+200*R8*Inputs!$C$3) +(R11*R9+200*R9*Inputs!$C$3) +R15*0.17*R1)+R14 -> 1005415.1 | S16: =3*(52/12)*S5* ((S10*S6+200*S6*Inputs!$C$3) +(S10*S7+200*S7*Inputs!$C$3) +(S10*S8+200*S8*Inputs!$C$3) +(S11*S9+200*S9*Inputs!$C$3) +S15*0.17*S1)+S14 -> 1219441 | T16: =3*(52/12)*T5* ((T10*T6+200*T6*Inputs!$C$3) +(T10*T7+200*T7*Inputs!$C$3) +(T10*T8+200*T8*Inputs!$C$3) +(T11*T9+200*T9*Inputs!$C$3) +T15*0.17*T1)+T14 -> 1436308 | U16: =3*(52/12)*U5* ((U10*U6+200*U6*Inputs!$C$3) +(U10*U7+200*U7*Inputs!$C$3) +(U10*U8+200*U8*Inputs!$C$3) +(U11*U9+200*U9*Inputs!$C$3) +U15*0.17*U1)+U14 -> 1656015.8 | V16: =3*(52/12)*V5* ((V10*V6+200*V6*Inputs!$C$3) +(V10*V7+200*V7*Inputs!$C$3) +(V10*V8+200*V8*Inputs!$C$3) +(V11*V9+200*V9*Inputs!$C$3) +V15*0.17*V1)+V14 -> 1878564.7
A17: (incl VAT) | B17: (incl BTW) | C17: =C16*1.21 -> 50649.682 | D17: =D16*1.21 -> 54703.181 | E17: =E16*1.21 -> 63496.204 | F17: =F16*1.21 -> 83644.211 | G17: =G16*1.21 -> 92560.363 | H17: =H16*1.21 -> 101516.2 | I17: =I16*1.21 -> 103441.66 | J17: =J16*1.21 -> 111895.54 | ... V17: =V16*1.21 -> 2273063.2
A19: total # of active users (renting at least once/month) | B19: totaal aan actieve gebruikers (die minimaal 1x/maand huren) | C19: =C20*Inputs!$C$10 -> 40.6 | D19: =D20*Inputs!$C$10 -> 44.1 | E19: =E20*Inputs!$C$10 -> 51.1 | F19: =F20*Inputs!$C$10 -> 63.7 | G19: =G20*Inputs!$C$10 -> 70.7 | H19: =H20*Inputs!$C$10 -> 77.7 | I19: =I20*Inputs!$C$10 -> 84.7 | J19: =J20*Inputs!$C$10 -> 91.7 | ... V19: =V20*Inputs!$C$10 -> 280.7
A20: total # of vehicles | B20: totale vloot | C20: =SUM(C6:C9) -> 29 | D20: =SUM(D6:D9) -> 31.5 | E20: =SUM(E6:E9) -> 36.5 | F20: =SUM(F6:F9) -> 45.5 | G20: =SUM(G6:G9) -> 50.5 | H20: =SUM(H6:H9) -> 55.5 | I20: =SUM(I6:I9) -> 60.5 | J20: =SUM(J6:J9) -> 65.5 | ... V20: =SUM(V6:V9) -> 200.5
A21: total kms driven | B21: aantal gereden kilometers | C21: =(52/12)*C5* ((C6*1500) +(C7*1500) +(C8*1500) +(C9*1500) +C15) -> 196542.67 | D21: =(52/12)*D5* ((D6*1500) +(D7*1500) +(D8*1500) +(D9*1500) +D15) -> 213486 | E21: =(52/12)*E5* ((E6*1500) +(E7*1500) +(E8*1500) +(E9*1500) +E15) -> 247372.67 | F21: =(52/12)*F5* ((F6*1500) +(F7*1500) +(F8*1500) +(F9*1500) +F15) -> 330057 | G21: =(52/12)*G5* ((G6*1500) +(G7*1500) +(G8*1500) +(G9*1500) +G15) -> 366327 | H21: =(52/12)*H5* ((H6*1500) +(H7*1500) +(H8*1500) +(H9*1500) +H15) -> 402597 | I21: =(52/12)*I5* ((I6*1500) +(I7*1500) +(I8*1500) +(I9*1500) +I15) -> 410028.67 | J21: =(52/12)*J5* ((J6*1500) +(J7*1500) +(J8*1500) +(J9*1500) +J15) -> 443915.33 | ... N21: =(52/12)*N5* ((N6*1500) +(N7*1500) +(N8*1500) +(N9*1500) +N15) -> 661713 | O21: =(52/12)*3*O5* ((O6*1500) +(O7*1500) +(O8*1500) +(O9*1500) +O15) -> 2239728.1 | P21: =(52/12)*3*P5* ((P6*1500) +(P7*1500) +(P8*1500) +(P9*1500) +P15) -> 2591517.8 | Q21: =(52/12)*3*Q5* ((Q6*1500) +(Q7*1500) +(Q8*1500) +(Q9*1500) +Q15) -> 2943307.6 | R21: =(52/12)*3*R5* ((R6*1500) +(R7*1500) +(R8*1500) +(R9*1500) +R15) -> 3295097.3 | S21: =(52/12)*3*S5* ((S6*1500) +(S7*1500) +(S8*1500) +(S9*1500) +S15) -> 3646887.1 | T21: =(52/12)*3*T5* ((T6*1500) +(T7*1500) +(T8*1500) +(T9*1500) +T15) -> 3998676.8 | U21: =(52/12)*3*U5* ((U6*1500) +(U7*1500) +(U8*1500) +(U9*1500) +U15) -> 4350466.6 | V21: =(52/12)*3*V5* ((V6*1500) +(V7*1500) +(V8*1500) +(V9*1500) +V15) -> 4702256.3
B22: gereden kilometers (eigen vloot) | C22: =(C8+C9)/C20*C21 -> 169433.33 | D22: =(D8+D9)/D20*D21 -> 169433.33 | E22: =(E8+E9)/E20*E21 -> 169433.33 | F22: =(F8+F9)/F20*F21 -> 210366 | G22: =(G8+G9)/G20*G21 -> 210366 | H22: =(H8+H9)/H20*H21 -> 210366 | I22: =(I8+I9)/I20*I21 -> 196542.67 | J22: =(J8+J9)/J20*J21 -> 196542.67 | ... V22: =(V8+V9)/V20*V21 -> 680126.85
A24: Variable COGS (Maintenance & EV charge) | B24: Inkoop variabel (ROB & stroom) | C24: =C1*(250*C5*C9+ 200*C5*C8+ 180*SUM(C6:C9)*Inputs!$C$3*(52/12)) -> 8493 | D24: =D1*(250*D5*D9+ 200*D5*D8+ 180*SUM(D6:D9)*Inputs!$C$3*(52/12)) -> 8807.4637 | E24: =E1*(250*E5*E9+ 200*E5*E8+ 180*SUM(E6:E9)*Inputs!$C$3*(52/12)) -> 9417.3525 | F24: =F1*(250*F5*F9+ 200*F5*F8+ 180*SUM(F6:F9)*Inputs!$C$3*(52/12)) -> 11529.326 | G24: =G1*(250*G5*G9+ 200*G5*G8+ 180*SUM(G6:G9)*Inputs!$C$3*(52/12)) -> 12148.785 | H24: =H1*(250*H5*H9+ 200*H5*H8+ 180*SUM(H6:H9)*Inputs!$C$3*(52/12)) -> 12771.169 | I24: =I1*(250*I5*I9+ 200*I5*I8+ 180*SUM(I6:I9)*Inputs!$C$3*(52/12)) -> 13051.377 | J24: =J1*(250*J5*J9+ 200*J5*J8+ 180*SUM(J6:J9)*Inputs!$C$3*(52/12)) -> 13678.761 | ... N24: =N1*(250*N5*N9+ 200*N5*N8+ 180*SUM(N6:N9)*Inputs!$C$3*(52/12)) -> 16916.246 | O24: =O1*3*(250*O5*O9+ 200*O5*O8+ 180*SUM(O6:O9)*Inputs!$C$3*(52/12)) -> 54752.017 | P24: =P1*3*(250*P5*P9+ 200*P5*P8+ 180*SUM(P6:P9)*Inputs!$C$3*(52/12)) -> 60637.534 | Q24: =Q1*3*(250*Q5*Q9+ 200*Q5*Q8+ 180*SUM(Q6:Q9)*Inputs!$C$3*(52/12)) -> 66602.025 | R24: =R1*3*(250*R5*R9+ 200*R5*R8+ 180*SUM(R6:R9)*Inputs!$C$3*(52/12)) -> 72645.491 | S24: =S1*3*(250*S5*S9+ 200*S5*S8+ 180*SUM(S6:S9)*Inputs!$C$3*(52/12)) -> 78767.932 | T24: =T1*3*(250*T5*T9+ 200*T5*T8+ 180*SUM(T6:T9)*Inputs!$C$3*(52/12)) -> 84969.349 | U24: =U1*3*(250*U5*U9+ 200*U5*U8+ 180*SUM(U6:U9)*Inputs!$C$3*(52/12)) -> 91249.74 | V24: =V1*3*(250*V5*V9+ 200*V5*V8+ 180*SUM(V6:V9)*Inputs!$C$3*(52/12)) -> 97609.106
A25: Fixed COGS (Lease, insurance & electronics) | B25: Inkoop vast (Lease, verzekering, electronica & BaaS) | C25: =C1*(C6*1230 +C7*Inputs!$C$9 +SUM(C7:C9)*230 +SUM(C7:C9)*15.9 +SUM(C7:C9)*25 +C9*238) -> 16452.5 | D25: =D1*(D6*1230 +D7*Inputs!$C$9 +SUM(D7:D9)*230 +SUM(D7:D9)*15.9 +SUM(D7:D9)*25 +D9*238) -> 19180.081 | E25: =E1*(E6*1230 +E7*Inputs!$C$9 +SUM(E7:E9)*230 +SUM(E7:E9)*15.9 +SUM(E7:E9)*25 +E9*238) -> 24614.209 | F25: =F1*(F6*1230 +F7*Inputs!$C$9 +SUM(F7:F9)*230 +SUM(F7:F9)*15.9 +SUM(F7:F9)*25 +F9*238) -> 31166.861 | G25: =G1*(G6*1230 +G7*Inputs!$C$9 +SUM(G7:G9)*230 +SUM(G7:G9)*15.9 +SUM(G7:G9)*25 +G9*238) -> 36657.293 | H25: =H1*(H6*1230 +H7*Inputs!$C$9 +SUM(H7:H9)*230 +SUM(H7:H9)*15.9 +SUM(H7:H9)*25 +H9*238) -> 42174.523 | I25: =I1*(I6*1230 +I7*Inputs!$C$9 +SUM(I7:I9)*230 +SUM(I7:I9)*15.9 +SUM(I7:I9)*25 +I9*238) -> 47718.55 | J25: =J1*(J6*1230 +J7*Inputs!$C$9 +SUM(J7:J9)*230 +SUM(J7:J9)*15.9 +SUM(J7:J9)*25 +J9*238) -> 53289.375 | ... N25: =N1*(N6*1230 +N7*Inputs!$C$9 +SUM(N7:N9)*230 +SUM(N7:N9)*15.9 +SUM(N7:N9)*25 +N9*238) -> 75840.648 | O25: =O1*3*(O6*1230 +O7*Inputs!$C$9 +SUM(O7:O9)*230 +SUM(O7:O9)*15.9 +SUM(O7:O9)*25 +O9*238) -> 262465.18 | P25: =P1*3*(P6*1230 +P7*Inputs!$C$9 +SUM(P7:P9)*230 +SUM(P7:P9)*15.9 +SUM(P7:P9)*25 +P9*238) -> 314652.61 | Q25: =Q1*3*(Q6*1230 +Q7*Inputs!$C$9 +SUM(Q7:Q9)*230 +SUM(Q7:Q9)*15.9 +SUM(Q7:Q9)*25 +Q9*238) -> 367563.58 | R25: =R1*3*(R6*1230 +R7*Inputs!$C$9 +SUM(R7:R9)*230 +SUM(R7:R9)*15.9 +SUM(R7:R9)*25 +R9*238) -> 421198.07 | S25: =S1*3*(S6*1230 +S7*Inputs!$C$9 +SUM(S7:S9)*230 +SUM(S7:S9)*15.9 +SUM(S7:S9)*25 +S9*238) -> 475556.1 | T25: =T1*3*(T6*1230 +T7*Inputs!$C$9 +SUM(T7:T9)*230 +SUM(T7:T9)*15.9 +SUM(T7:T9)*25 +T9*238) -> 530637.66 | U25: =U1*3*(U6*1230 +U7*Inputs!$C$9 +SUM(U7:U9)*230 +SUM(U7:U9)*15.9 +SUM(U7:U9)*25 +U9*238) -> 586442.75 | V25: =V1*3*(V6*1230 +V7*Inputs!$C$9 +SUM(V7:V9)*230 +SUM(V7:V9)*15.9 +SUM(V7:V9)*25 +V9*238) -> 642971.38
A26: Driveplan direct costs | B26: Driveplan directe kosten (server & tokens) | O26: =(O12+O13)*15*O1 -> 963.71437 | P26: =(P12+P13)*15*P1 -> 1123.1634 | Q26: =(Q12+Q13)*15*Q1 -> 4434.8062 | R26: =(R12+R13)*15*R1 -> 7793.6428 | S26: =(S12+S13)*15*S1 -> 11199.673 | T26: =(T12+T13)*15*T1 -> 14652.897 | U26: =(U12+U13)*15*U1 -> 18153.315 | V26: =(V12+V13)*15*V1 -> 21700.927
A27: Total COGS | B27: Totaal Inkoop | C27: =C24+C25+C26 -> 24945.5 | D27: =D24+D25+D26 -> 27987.544 | E27: =E24+E25+E26 -> 34031.561 | F27: =F24+F25+F26 -> 42696.188 | G27: =G24+G25+G26 -> 48806.078 | H27: =H24+H25+H26 -> 54945.692 | I27: =I24+I25+I26 -> 60769.928 | J27: =J24+J25+J26 -> 66968.136 | ... V27: =V24+V25+V26 -> 762281.41
A29: Gross Profit | B29: Brutomarge | C29: =C16-C27 -> 16913.742 | D29: =D16-D27 -> 17221.696 | E29: =E16-E27 -> 18444.64 | F29: =F16-F27 -> 26431.26 | G29: =G16-G27 -> 27690.089 | H29: =H16-H27 -> 28951.995 | I29: =I16-I27 -> 24719.051 | J29: =J16-J27 -> 25507.514 | ... V29: =V16-V27 -> 1116283.3
A30: Groos Profit Margin (% Revenue) | B30: Brutomarge (% omzet) | C30: =C29/C16 -> 0.4040623 | D30: =D29/D16 -> 0.3809331 | E30: =E29/E16 -> 0.35148581 | F30: =F29/F16 -> 0.3823555 | G30: =G29/G16 -> 0.36198008 | H30: =H29/H16 -> 0.34508693 | I30: =I29/I16 -> 0.28914898 | J30: =J29/J16 -> 0.27582952 | ... V30: =V29/V16 -> 0.59422136
A32: Housing costs / Facilities costs | B32: Huisvestingskosten (Parkeergarage, kantoor) | C32: =C1*(1430.12+1500) -> 2930.12 | D32: =D1*(1430.12+1500) -> 2937.4453 | E32: =E1*(1430.12+3500) -> 4954.7706 | F32: =F1*(1430.12+3500) -> 4967.0959 | G32: =G1*(1430.12+3500) -> 4979.4212 | H32: =H1*(1430.12+3500) -> 4991.7465 | I32: =I1*(1430.12+3500) -> 5004.0718 | J32: =J1*(1430.12+3500) -> 5016.3971 | K32: =K1*(1430.12+3500) -> 5028.7224 | L32: =L1*(1430.12+3500) -> 5041.0477 | ... N32: =N1*(1430.12+3500) -> 5065.6983 | O32: =O1*3*(1430.12+3500*(((O33/3)-N33)/(N33)+1)) -> 15358.543 | P32: =P1*3*(1430.12+3500*((Q33-P33)/(P33)+1)) -> 15498.011 | Q32: =Q1*3*(1430.12+3500*((R33-Q33)/(Q33)+1)) -> 15608.936 | R32: =R1*3*(1430.12+3500*((S33-R33)/(R33)+1)) -> 15719.862 | S32: =S1*3*(1430.12+3500*((T33-S33)/(S33)+1)) -> 15830.787 | T32: =T1*3*(1430.12+3500*((U33-T33)/(T33)+1)) -> 15941.713 | U32: =U1*3*(1430.12+3500*((V33-U33)/(U33)+1)) -> 16052.639 | V32: =U32 -> 16052.639
A33: Personnel costs | B33: Personeelkosten (incl WBSO subsidie) | C33: =C1*12500+C34 -> 14150 | D33: =D1*12500+D34 -> 14181.25 | E33: =E1*16000+E34 -> 17730 | F33: =F1*16000+F34 -> 24834.875 | G33: =G1*16000+G34 -> 24896.5 | H33: =H1*16000+H34 -> 24958.125 | I33: =I1*16000+I34 -> 30668.125 | J33: =J1*21000+J34 -> 35831.25 | K33: =K1*21000+K34 -> 35919.375 | L33: =L1*21000+L34 -> 47227.5 | M33: =M1*21000+M34 -> 47343.125 | N33: =N1*21000+N34 -> 47458.75 | O33: =3*O1*21000+O34 -> 143038.12 | P33: =3*P1*21000+P34 -> 144078.75 | Q33: =3*Q1*21000+Q34 -> 145119.37 | R33: =3*R1*21000+R34 -> 146160 | S33: =3*S1*21000+S34 -> 147200.62 | T33: =3*T1*21000+T34 -> 148241.25 | U33: =3*U1*21000+U34 -> 149281.87 | V33: =3*V1*21000+V34 -> 150322.5
A34: Of which DrivePlan team | B34: Waarvan Driveplan | C34: 1650 | D34: 1650 | E34: 1650 | F34: =8650*F1 -> 8714.875 | G34: =8650*G1 -> 8736.5 | H34: =8650*H1 -> 8758.125 | I34: =14250*H1 -> 14428.125 | J34: =14250*I1 -> 14463.75 | K34: =14250*J1 -> 14499.375 | L34: =25250*K1 -> 25755 | M34: =25250*L1 -> 25818.125 | N34: =25250*M1 -> 25881.25 | O34: =3*25250*N1 -> 77833.125 | P34: =3*25250*O1 -> 78401.25 | Q34: =3*25250*P1 -> 78969.375 | R34: =3*25250*Q1 -> 79537.5 | S34: =3*25250*R1 -> 80105.625 | T34: =3*25250*S1 -> 80673.75 | U34: =3*25250*T1 -> 81241.875 | V34: =3*25250*U1 -> 81810
A35: Sales costs (0.5%) | B35: Verkoopkosten (1%) | C35: =C16*0.01 -> 418.59242 | D35: =D16*0.01 -> 452.0924 | E35: =E16*0.01 -> 524.76201 | F35: =F16*0.01 -> 691.27447 | G35: =G16*0.01 -> 764.96168 | H35: =H16*0.01 -> 838.97687 | I35: =I16*0.01 -> 854.88979 | J35: =J16*0.01 -> 924.7565 | ... V35: =V16*0.01 -> 18785.647
A36: Marketing costs (2%) | B36: Marketing kosten (3%) | C36: =C16*0.03 -> 1255.7772 | D36: =D16*0.03 -> 1356.2772 | E36: =E16*0.03 -> 1574.286 | F36: =F16*0.03 -> 2073.8234 | G36: =G16*0.03 -> 2294.885 | H36: =H16*0.03 -> 2516.9306 | I36: =I16*0.03 -> 2564.6694 | J36: =J16*0.03 -> 2774.2695 | ... V36: =V16*0.03 -> 56356.94
A37: Application management costs (Software, app) | B37: Applicatiebeheer kosten (Software, app) | C37: =C1*(299+471+1155/3+200) -> 1355 | D37: =D1*(299+471+1155/3+200) -> 1358.3875 | E37: =E1*(299+471+1155/3+200) -> 1361.775 | F37: =F1*(299+471+1155/3+200) -> 1365.1625 | G37: =G1*(299+471+1155/3+200) -> 1368.55 | H37: =H1*(299+471+1155/3+200+7900) -> 9370.6875 | I37: =I1*(299+471+1155/3+200) -> 1375.325 | J37: =J1*(299+471+1155/3+200) -> 1378.7125 | K37: =K1*(299+471+1155/3+200) -> 1382.1 | L37: =L1*(299+471+1155/3+200) -> 1385.4875 | M37: =M1*(299+471+1155/3+200) -> 1388.875 | N37: =N1*(299+471+1155/3+200) -> 1392.2625 | O37: =O1*(3*(299+471+1555+200))+7900/4 -> 9815.125 | P37: =P1*(3*(299+471+1555+200))+7900/4 -> 9871.9375 | Q37: =Q1*(3*(299+471+1555+200))+7900/4 -> 9928.75 | R37: =R1*(3*(299+471+1555+200))+7900/4 -> 9985.5625 | S37: =S1*(3*(299+471+1555+200))+7900/4 -> 10042.375 | T37: =T1*(3*(299+471+1555+200))+7900/4 -> 10099.187 | U37: =U1*(3*(299+471+1555+200))+7900/4 -> 10156 | V37: =V1*(3*(299+471+1555+200))+7900/4 -> 10212.812
A38: General & administrative costs (Accounting, legal) | B38: Algemene kosten (Accountancy, legal) | C38: 2000 | D38: 2040 | E38: 2080.8 | F38: 2122.416 | G38: 2164.8643 | H38: 2208.1616 | I38: 2252.3248 | J38: 2297.3713 | K38: 2343.3188 | L38: 2390.1851 | M38: 2437.9888 | N38: 2486.7486 | O38: 7609.4508 | P38: 7761.6398 | Q38: 7916.8726 | R38: 8075.21 | S38: 8236.7142 | T38: 8401.4485 | U38: 8569.4775 | V38: 8740.867
A39: Management fee expenses | B39: Managementfee kosten | C39: =9212*1.035 -> 9534.42 | D39: =9212*1.035 -> 9534.42 | E39: =9212*1.035 -> 9534.42 | F39: =9212*1.035 -> 9534.42 | G39: =9212*1.035 -> 9534.42 | H39: =9212*1.035 -> 9534.42 | I39: =9212*1.035 -> 9534.42 | J39: =9212*1.035 -> 9534.42 | ... N39: =9212*1.035 -> 9534.42 | O39: =3*9212*1.035*O1 -> 29604.374 | P39: =3*9212*1.035*P1 -> 29818.899 | Q39: =3*9212*1.035*Q1 -> 30033.423 | R39: =3*9212*1.035*R1 -> 30247.947 | S39: =3*9212*1.035*S1 -> 30462.472 | T39: =3*9212*1.035*T1 -> 30676.996 | U39: =3*9212*1.035*U1 -> 30891.521 | V39: =3*9212*1.035*V1 -> 31106.045
A40: Total OPEX | B40: Totaal Bedrijfskosten | C40: =SUM(C32:C39)-C34 -> 31643.91 | D40: =SUM(D32:D39)-D34 -> 31859.872 | E40: =SUM(E32:E39)-E34 -> 37760.814 | F40: =SUM(F32:F39)-F34 -> 45589.067 | G40: =SUM(G32:G39)-G34 -> 46003.602 | H40: =SUM(H32:H39)-H34 -> 54419.048 | I40: =SUM(I32:I39)-I34 -> 52253.826 | J40: =SUM(J32:J39)-J34 -> 57757.177 | ... V40: =SUM(V32:V39)-V34 -> 291577.45
A42: EBITDA | B42: EBITDA | C42: =C29-C40 -> -14730.168 | D42: =D29-D40 -> -14638.177 | E42: =E29-E40 -> -19316.174 | F42: =F29-F40 -> -19157.808 | G42: =G29-G40 -> -18313.513 | H42: =H29-H40 -> -25467.053 | I42: =I29-I40 -> -27534.775 | J42: =J29-J40 -> -32249.663 | ... V42: =V29-V40 -> 824705.81
B44: Investeringsbehoefte | C44: =C42 -> -14730.168 | D44: =D42 -> -14638.177 | E44: =E42 -> -19316.174 | F44: =F42 -> -19157.808 | G44: =G42 -> -18313.513 | H44: =H42 -> -25467.053 | I44: =I42 -> -27534.775 | J44: =J42 -> -32249.663 | ... P44: =P42 -> -20992.059
B45: Onvoorzien | C45: -14767.692
B47: Totale behoefte | C47: =SUM(C44:R45) -> -350000.08
